setup.py
fsm/__init__.py
fsm/core.py
fsm/parsers.py
hsme.egg-info/PKG-INFO
hsme.egg-info/SOURCES.txt
hsme.egg-info/dependency_links.txt
hsme.egg-info/top_level.txt
tests/__init__.py
tests/test_parsers.py
tests/test_process.py
tests/charts/__init__.py
tests/charts/rules.py